aegis/__init__.py
aegis/_version.py
aegis/approval_queue.py
aegis/config.py
aegis/decision.py
aegis/errors.py
aegis/executor.py
aegis/guard.py
aegis/http.py
aegis/logging.py
aegis/polling.py
aegis/py.typed
aegis/task_manager.py
aegis/types.py
aegis/util.py
aegislib-0.1.4.dist-info/licenses/LICENSE
aegislib-0.1.4.dist-info/METADATA
aegislib-0.1.4.dist-info/WHEEL
aegislib-0.1.4.dist-info/top_level.txt
aegislib-0.1.4.dist-info/RECORD
