Metadata-Version: 2.4
Name: aegislib
Version: 0.1.4
Summary: Aegis Python SDK - Secure AI agents tool guard integration
Home-page: https://github.com/mrsidrdx/aegis-python-sdk
Author: Siddhartha Satyakama
Author-email: Aegis Team <bithal06@gmail.com>
Maintainer-email: mrsidrdx <bithal06@gmail.com>
License: MIT
Project-URL: Homepage, https://github.com/mrsidrdx/aegis-python-sdk
Project-URL: Documentation, https://github.com/mrsidrdx/aegis-python-sdk
Project-URL: Repository, https://github.com/mrsidrdx/aegis-python-sdk
Project-URL: Issues, https://github.com/mrsidrdx/aegis-python-sdk/issues
Keywords: ai,security,policy,agent,tool,guard
Classifier: Development Status :: 4 - Beta
Classifier: Intended Audience :: Developers
Classifier: License :: OSI Approved :: MIT License
Classifier: Operating System :: OS Independent
Classifier: Programming Language :: Python :: 3
Classifier: Programming Language :: Python :: 3.11
Classifier: Programming Language :: Python :: 3.12
Classifier: Programming Language :: Python :: 3.13
Classifier: Topic :: Security
Classifier: Topic :: Software Development :: Libraries :: Python Modules
Requires-Python: >=3.11
License-File: LICENSE
Requires-Dist: httpx>=0.25.0
Requires-Dist: pydantic>=2.0.0
Requires-Dist: backoff>=2.2.0
Provides-Extra: dev
Requires-Dist: pytest>=7.4.0; extra == "dev"
Requires-Dist: pytest-cov>=4.1.0; extra == "dev"
Requires-Dist: pytest-asyncio>=0.21.0; extra == "dev"
Requires-Dist: pytest-mock>=3.12.0; extra == "dev"
Requires-Dist: black>=23.0.0; extra == "dev"
Requires-Dist: ruff>=0.1.0; extra == "dev"
Requires-Dist: isort>=5.12.0; extra == "dev"
Requires-Dist: mypy>=1.7.0; extra == "dev"
Requires-Dist: build>=1.0.0; extra == "dev"
Requires-Dist: twine>=4.0.0; extra == "dev"
Provides-Extra: test
Requires-Dist: pytest>=7.4.0; extra == "test"
Requires-Dist: pytest-cov>=4.1.0; extra == "test"
Requires-Dist: pytest-asyncio>=0.21.0; extra == "test"
Requires-Dist: pytest-mock>=3.12.0; extra == "test"
Dynamic: license-file
